{
  "_format": "hh-sol-cache-2",
  "files": {
    "/home/vaibhav/projects/Medical-Record-With-Blockchain/Web App/hardhat-project/contracts/doctorcontract.sol": {
      "lastModificationDate": 1768740513251,
      "contentHash": "714390ef5b99e908ffd4f78705f1ee7c",
      "sourceName": "contracts/doctorcontract.sol",
      "solcConfig": {
        "version": "0.8.24",
        "settings": {
          "evmVersion": "paris",
          "optimizer": {
            "enabled": false,
            "runs": 200
          },
          "outputSelection": {
            "*": {
              "*": [
                "abi",
                "evm.bytecode",
                "evm.deployedBytecode",
                "evm.methodIdentifiers",
                "metadata"
              ],
              "": [
                "ast"
              ]
            }
          }
        }
      },
      "imports": [],
      "versionPragmas": [
        "^0.8.0"
      ],
      "artifacts": [
        "DoctorManagement"
      ]
    },
    "/home/vaibhav/projects/Medical-Record-With-Blockchain/Web App/hardhat-project/contracts/patientcontract.sol": {
      "lastModificationDate": 1768740619057,
      "contentHash": "31a6862b406a966de345e8728406162e",
      "sourceName": "contracts/patientcontract.sol",
      "solcConfig": {
        "version": "0.8.24",
        "settings": {
          "evmVersion": "paris",
          "optimizer": {
            "enabled": false,
            "runs": 200
          },
          "outputSelection": {
            "*": {
              "*": [
                "abi",
                "evm.bytecode",
                "evm.deployedBytecode",
                "evm.methodIdentifiers",
                "metadata"
              ],
              "": [
                "ast"
              ]
            }
          }
        }
      },
      "imports": [],
      "versionPragmas": [
        "^0.8.0"
      ],
      "artifacts": [
        "IDoctorManagement",
        "PatientManagement"
      ]
    }
  }
}
